{"data":{"properties":{"id":{"name":"id","reference":"scalar","primary":true,"type":"number","array":false},"nic":{"name":"nic","reference":"scalar","type":"varchar","length":45,"getter":false,"setter":false,"array":false},"hospital_id":{"name":"hospital_id","reference":"scalar","getter":false,"setter":false,"type":"number","array":false},"changed_by":{"name":"changed_by","reference":"scalar","type":"varchar","length":45,"getter":false,"setter":false,"array":false},"type":{"name":"type","reference":"scalar","type":"varchar","length":45,"getter":false,"setter":false,"array":false},"timestamp":{"name":"timestamp","reference":"scalar","getter":false,"setter":false,"type":"Date","array":false},"field":{"name":"field","reference":"scalar","type":"varchar","length":255,"getter":false,"setter":false,"array":false},"previous_value_id":{"name":"previous_value_id","reference":"scalar","getter":false,"setter":false,"type":"number","array":false},"value":{"name":"value","reference":"scalar","getter":false,"setter":false,"type":"string","array":false}},"primaryKeys":["id"],"filters":{},"hooks":{},"indexes":[],"uniques":[],"className":"LogChanges","path":"./dist/entities/logchanges/logchanges.entity.js","collection":"logchanges","name":"LogChanges","abstract":false,"constructorParams":[],"toJsonParams":[],"useCache":true,"compositePK":false,"simplePK":true},"origin":"./dist/entities/logchanges/logchanges.entity.js","hash":"cd38d079099014b712181197a01cbb77","version":"5.9.7"}
